openhltspirent/__init__.py
openhltspirent/httptransport.py
openhltspirent/openhltspirent.py
openhltspirent/yangbase.py
openhltspirent/docs/openhltspirent.html
openhltspirent/samples/bfd_bgp4_sample_script.py
openhltspirent/samples/bfd_bgp6_sample_script.py
openhltspirent/samples/bgpv4_sample_script.py
openhltspirent/samples/bgpv6_sample_script.py
openhltspirent/samples/bound_stream_sample_script.py
openhltspirent/samples/dhcpv4_sample_script.py
openhltspirent/samples/dhcpv6_sample_script.py
openhltspirent/samples/icmpv4_headers_sample_script.py
openhltspirent/samples/icmpv6_headers_sample_script.py
openhltspirent/samples/igmp_headers_sample_script.py
openhltspirent/samples/igmp_sample_script.py
openhltspirent/samples/isisv4_sample_script.py
openhltspirent/samples/isisv6_sample_script.py
openhltspirent/samples/ospfv2_headers_sample_script.py
openhltspirent/samples/ospfv2_sample_script.py
openhltspirent/samples/ospfv3_sample_script.py
openhltspirent/samples/raw_stream_sample_script.py
openhltspirent/samples/verify_traffic_sample_script.py
openhltspirent-1.0.108.dist-info/METADATA
openhltspirent-1.0.108.dist-info/WHEEL
openhltspirent-1.0.108.dist-info/top_level.txt
openhltspirent-1.0.108.dist-info/RECORD
