Metadata-Version: 2.1
Name: openhltspirent
Version: 1.0.108
Summary: OpenHLTest Python Client
Home-page: https://github.com/SpirentCom/OpenHLtest/models
Author: BDC-xTAPI-Eng
Author-email: BDC-xTAPI-Eng@spirent.com
License: MIT
Keywords: openhltest test tool spirent restconf automation
Platform: UNKNOWN
Classifier: Development Status :: 3 - Alpha
Classifier: Intended Audience :: Developers
Classifier: Topic :: Software Development
Classifier: License :: OSI Approved :: MIT License
Classifier: Programming Language :: Python :: 2.7
Classifier: Programming Language :: Python :: 3
Requires-Python: >=2.7, <4
Requires-Dist: requests
